plotdata/__init__.py
plotdata/helper_functions.py
plotdata/process_data.py
plotdata/volcano_functions.py
plotdata/cli/__init__.py
plotdata/cli/global_location.py
plotdata/cli/list_volcanoes.py
plotdata/cli/plot_data.py
plotdata/objects/__init__.py
plotdata/objects/create_map.py
plotdata/objects/earthquakes.py
plotdata/objects/get_methods.py
plotdata/objects/plot_properties.py
plotdata/objects/plotters.py
plotdata/objects/process_data.py
plotdata/objects/section.py
plotdata/utils/__init__.py
plotdata/utils/argument_parsers.py
minsarplotdata-0.1.4.dist-info/METADATA
minsarplotdata-0.1.4.dist-info/WHEEL
minsarplotdata-0.1.4.dist-info/entry_points.txt
minsarplotdata-0.1.4.dist-info/top_level.txt
minsarplotdata-0.1.4.dist-info/RECORD
