Metadata-Version: 2.4
Name: MinsarPlotData
Version: 0.1.4
Summary: A package for plotting InSAR and Seismicity data
Author: Giacomo Di Silvestro
Author-email: gxd593@miami.edu
Requires-Python: >=3.6
Requires-Dist: numpy
Requires-Dist: matplotlib
Requires-Dist: pygmt
Requires-Dist: xarray
Requires-Dist: pandas
Requires-Dist: cartopy
Requires-Dist: jupyter-ai
Requires-Dist: scipy
Requires-Dist: scikit-learn
Requires-Dist: simplekml
Requires-Dist: geopandas
Requires-Dist: mintpy
Dynamic: author
Dynamic: author-email
Dynamic: description
Dynamic: description-content-type
Dynamic: requires-dist
Dynamic: requires-python
Dynamic: summary
